lagtraj/__init__.py
lagtraj/domain/__init__.py
lagtraj/domain/download.py
lagtraj/domain/download_by_trajectory.py
lagtraj/domain/load.py
lagtraj/domain/mask.py
lagtraj/domain/sources/__init__.py
lagtraj/domain/sources/common.py
lagtraj/domain/sources/dummy.py
lagtraj/domain/sources/era5/137levels.dat
lagtraj/domain/sources/era5/__init__.py
lagtraj/domain/sources/era5/aux_variables.py
lagtraj/domain/sources/era5/cdsapi_request.py
lagtraj/domain/sources/era5/constants.py
lagtraj/domain/sources/era5/download.py
lagtraj/domain/sources/era5/interpolation.py
lagtraj/domain/sources/era5/load.py
lagtraj/domain/sources/era5/utils.py
lagtraj/forcings/__init__.py
lagtraj/forcings/create.py
lagtraj/forcings/load.py
lagtraj/forcings/plot.py
lagtraj/forcings/profile_calculation.py
lagtraj/forcings/conversion/__init__.py
lagtraj/forcings/conversion/era5.py
lagtraj/forcings/conversion/input_definitions.py
lagtraj/forcings/conversion/load.py
lagtraj/forcings/conversion/process.py
lagtraj/forcings/conversion/targets/__init__.py
lagtraj/forcings/conversion/targets/dephy.py
lagtraj/forcings/conversion/targets/kpt.py
lagtraj/input_definitions/__init__.py
lagtraj/input_definitions/examples.py
lagtraj/input_definitions/load.py
lagtraj/input_definitions/examples_files/domains/drydown_cardington_local.yaml
lagtraj/input_definitions/examples_files/domains/eurec4a_circle.yaml
lagtraj/input_definitions/examples_files/domains/eurec4a_north_atlantic.yaml
lagtraj/input_definitions/examples_files/forcings/drydown_cardington_20200420_00_eul.yaml
lagtraj/input_definitions/examples_files/forcings/eurec4a_20200103_lag_testcase.yaml
lagtraj/input_definitions/examples_files/forcings/eurec4a_20200128_first.yaml
lagtraj/input_definitions/examples_files/forcings/eurec4a_20200202_first.yaml
lagtraj/input_definitions/examples_files/forcings/eurec4a_20200202_first_short.yaml
lagtraj/input_definitions/examples_files/forcings/eurec4a_20200202_first_short_eul.yaml
lagtraj-0.1.2.dist-info/LICENSE
lagtraj-0.1.2.dist-info/METADATA
lagtraj-0.1.2.dist-info/WHEEL
lagtraj-0.1.2.dist-info/top_level.txt
lagtraj-0.1.2.dist-info/RECORD
