Metadata-Version: 2.1
Name: lagtraj
Version: 0.1.2
Summary: Python trajectory code for Lagrangian simulations
Home-page: https://github.com/EUREC4A-UK/lagtraj
Author: Leif Denby
Author-email: l.c.denby@leeds.ac.uk
License-File: LICENSE
Requires-Dist: xarray (>=0.16.0)
Requires-Dist: pytest
Requires-Dist: netCDF4
Requires-Dist: datetime
Requires-Dist: numpy
Requires-Dist: pyyaml
Requires-Dist: cdsapi
Requires-Dist: pandas (!=1.1.0)
Requires-Dist: scipy
Requires-Dist: argparse
Requires-Dist: dask[array]
Requires-Dist: asciitree
Requires-Dist: isodate
Requires-Dist: psutil
Requires-Dist: semver (==2.13.0)
Requires-Dist: numba
Provides-Extra: dev
Requires-Dist: pytest ; extra == 'dev'
Requires-Dist: pre-commit ; extra == 'dev'
Requires-Dist: ipython ; extra == 'dev'
Provides-Extra: test
Requires-Dist: pytest ; extra == 'test'
